torch_survival/__init__.py
torch_survival/config.py
torch_survival/losses.py
torch_survival/metrics.py
torch_survival/models/__init__.py
torch_survival/models/deephit.py
torch_survival/models/deepsurv.py
torch_survival/models/rankdeepsurv.py
torch_survival/models/weibull.py
torch_survival/progress.py
torch_survival/py.typed
torch_survival/sample.py
torch_survival/utils.py
torch_survival-0.1.0a6.dist-info/WHEEL
torch_survival-0.1.0a6.dist-info/METADATA
torch_survival-0.1.0a6.dist-info/RECORD
