Metadata-Version: 2.3
Name: torch-survival
Version: 0.1.0a6
Summary: Production-ready deep survival analysis with one line of code
Requires-Dist: matplotlib>=3.10.8
Requires-Dist: optuna>=4.5.0
Requires-Dist: optuna-integration[sklearn]>=4.6.0
Requires-Dist: pycox>=0.3.0
Requires-Dist: rich>=14.2.0
Requires-Dist: scikit-survival>=0.24.1
Requires-Dist: torch>=2.8.0
Requires-Dist: typing-extensions>=4.15.0
Requires-Dist: furo>=2025.7.19 ; extra == 'docs'
Requires-Dist: sphinx>=8.2.3 ; extra == 'docs'
Requires-Dist: h5py>=3.14.0 ; extra == 'test'
Requires-Dist: torchsurv>=0.1.5 ; extra == 'test'
Requires-Python: >=3.12
Provides-Extra: docs
Provides-Extra: test
